a2a_handler/__init__.py
a2a_handler/auth.py
a2a_handler/cli/__init__.py
a2a_handler/cli/_config.py
a2a_handler/cli/_helpers.py
a2a_handler/cli/auth.py
a2a_handler/cli/card.py
a2a_handler/cli/mcp.py
a2a_handler/cli/message.py
a2a_handler/cli/server.py
a2a_handler/cli/session.py
a2a_handler/cli/task.py
a2a_handler/common/__init__.py
a2a_handler/common/config.py
a2a_handler/common/logging.py
a2a_handler/common/output.py
a2a_handler/mcp/__init__.py
a2a_handler/mcp/server.py
a2a_handler/server/__init__.py
a2a_handler/server/agent.py
a2a_handler/server/app.py
a2a_handler/server/card.py
a2a_handler/server/ollama.py
a2a_handler/service.py
a2a_handler/session.py
a2a_handler/tui/__init__.py
a2a_handler/tui/app.py
a2a_handler/tui/app.tcss
a2a_handler/tui/components/__init__.py
a2a_handler/tui/components/artifacts.py
a2a_handler/tui/components/auth.py
a2a_handler/tui/components/card.py
a2a_handler/tui/components/contact.py
a2a_handler/tui/components/input.py
a2a_handler/tui/components/logs.py
a2a_handler/tui/components/messages.py
a2a_handler/tui/components/tasks.py
a2a_handler/validation.py
a2a_handler/webhook.py
a2a_handler-0.1.15.dist-info/licenses/LICENSE
a2a_handler-0.1.15.dist-info/WHEEL
a2a_handler-0.1.15.dist-info/entry_points.txt
a2a_handler-0.1.15.dist-info/METADATA
a2a_handler-0.1.15.dist-info/RECORD
