Metadata-Version: 2.4
Name: a2a-handler
Version: 0.1.15
Summary: An A2A Protocol client TUI and CLI.
Keywords: a2a,a2a-protocol,agent,agent-to-agent,ai,cli,tui
Author: Al Duncanson
Author-email: Al Duncanson <alDuncanson@proton.me>
License-Expression: GPL-3.0-or-later
License-File: LICENSE
Classifier: Development Status :: 4 - Beta
Classifier: Environment :: Console
Classifier: Intended Audience :: Developers
Classifier: License :: OSI Approved :: GNU General Public License v3 or later (GPLv3+)
Classifier: Operating System :: OS Independent
Classifier: Programming Language :: Python :: 3
Classifier: Programming Language :: Python :: 3.11
Classifier: Programming Language :: Python :: 3.12
Classifier: Programming Language :: Python :: 3.13
Classifier: Topic :: Software Development :: Libraries :: Python Modules
Classifier: Typing :: Typed
Requires-Dist: a2a-sdk>=0.3.22
Requires-Dist: click>=8.0.0
Requires-Dist: rich-click>=1.8.0
Requires-Dist: google-adk>=0.5.0
Requires-Dist: httpx>=0.27.0
Requires-Dist: litellm>=1.0.0
Requires-Dist: python-dotenv>=1.0.0
Requires-Dist: rich>=13.0.0
Requires-Dist: textual>=0.47.0
Requires-Dist: uvicorn>=0.30.0
Requires-Dist: textual-serve>=1.1.0
Requires-Dist: mcp[cli]>=1.2.0
Requires-Dist: truststore>=0.9.0
Requires-Python: >=3.11
Project-URL: Homepage, https://github.com/alDuncanson/handler
Project-URL: Repository, https://github.com/alDuncanson/handler
Project-URL: Documentation, https://github.com/alDuncanson/handler#readme
Project-URL: Issues, https://github.com/alDuncanson/handler/issues
Project-URL: Changelog, https://github.com/alDuncanson/handler/releases
